{
  "checkpoint": "habla-safe-guidance-right-modal",
  "createdAt": "2026-05-25T11:19:19.957845+00:00",
  "document": "docs/security/habla_bloqueo_con_alternativa_segura.md",
  "patchedFiles": [
    "frontend/src/App.jsx",
    "frontend/src/App.css"
  ],
  "uiBehavior": {
    "button": "Ver direccion segura",
    "greenRightPanel": "direccion_segura_valida_alternativa_siguientes_pasos",
    "redModal": "accion_negada_razon_evidencia"
  },
  "validations": [
    "npm --prefix frontend run build",
    "OPEN_BROWSER=0 ./start.sh restart"
  ]
}